sappho
