Metadata-Version: 1.1
Name: sappho
Version: 0.14.2
Summary: 2D game engine (pygame)
Home-page: UNKNOWN
Author: Lillian Lemmer
Author-email: lillian.lemmer@hypatiasoftware.org
License: MIT
Keywords: games gaming development sprites adventure game tilemap tilesheet zelda gamedev 2d
Platform: UNKNOWN
Classifier: Development Status :: 3 - Alpha
Classifier: Intended Audience :: Developers
Classifier: Natural Language :: English
Classifier: License :: OSI Approved :: MIT License
Classifier: Programming Language :: Python :: 2.7
Classifier: Programming Language :: Python :: 3.4
Classifier: Topic :: Games/Entertainment :: Role-Playing
Classifier: Topic :: Software Development :: Libraries :: pygame
